patentgpt
