Metadata-Version: 2.1
Name: patentgpt-extract
Version: 0.1.7
Summary: A package for downloading and analysisng us patents.
Author: Armin Norouzi
Author-email: arminnorouzi2016@gmail.com
Project-URL: Bug Tracker, https://github.com/arminnorouzi/patentGPT/issues
Project-URL: Source Code, https://github.com/arminnorouzi/patentGPT
License-File: LICENSE
